aliyunsdkamptest/__init__.py
aliyunsdkamptest/request/__init__.py
aliyunsdkamptest/request/v20201230/CreateRulesRequest.py
aliyunsdkamptest/request/v20201230/HuichengTestGrayEightRequest.py
aliyunsdkamptest/request/v20201230/HuichengTestGrayFifthRequest.py
aliyunsdkamptest/request/v20201230/HuichengTestGrayNineRequest.py
aliyunsdkamptest/request/v20201230/HuichengTestGrayRequest.py
aliyunsdkamptest/request/v20201230/HuichengTestGraySecondRequest.py
aliyunsdkamptest/request/v20201230/HuichengTestGraySevenRequest.py
aliyunsdkamptest/request/v20201230/HuichengTestGraySixRequest.py
aliyunsdkamptest/request/v20201230/HuichengTestGrayTenRequest.py
aliyunsdkamptest/request/v20201230/HuichengTestGrayThirdRequest.py
aliyunsdkamptest/request/v20201230/HuichengTestResourceOwnerIdRequest.py
aliyunsdkamptest/request/v20201230/HuichengetRequest.py
aliyunsdkamptest/request/v20201230/HuichengetestRequest.py
aliyunsdkamptest/request/v20201230/__init__.py
aliyun_python_sdk_amptest-1.0.0.dist-info/LICENSE
aliyun_python_sdk_amptest-1.0.0.dist-info/METADATA
aliyun_python_sdk_amptest-1.0.0.dist-info/WHEEL
aliyun_python_sdk_amptest-1.0.0.dist-info/top_level.txt
aliyun_python_sdk_amptest-1.0.0.dist-info/RECORD
